YahooProject/__init__.py
YahooProject/search.py
YahooProject-1.1.dist-info/METADATA
YahooProject-1.1.dist-info/WHEEL
YahooProject-1.1.dist-info/top_level.txt
YahooProject-1.1.dist-info/RECORD
