Metadata-Version: 2.1
Name: YahooProject
Version: 1.1
Summary: A package for scraping search results from Yahoo Search.
Author: Nick37
Classifier: Programming Language :: Python :: 3
Classifier: License :: OSI Approved :: MIT License
Classifier: Operating System :: OS Independent
Requires-Dist: requests
Requires-Dist: beautifulsoup4
